.travis.yml
AUTHORS
ChangeLog
LICENSE
README.md
requirements.txt
setup.cfg
setup.py
test-requirements.txt
smoothie/__init__.py
smoothie/king.py
smoothie.egg-info/PKG-INFO
smoothie.egg-info/SOURCES.txt
smoothie.egg-info/dependency_links.txt
smoothie.egg-info/not-zip-safe
smoothie.egg-info/pbr.json
smoothie.egg-info/top_level.txt
smoothie/exc/__init__.py
smoothie/tests/__init__.py
smoothie/tests/test_smoothie.py