Metadata-Version: 1.1
Name: smoothie
Version: 0.1.dev14
Summary: summary
Home-page: https://github.com/TheSriram/smoothie
Author: Sriram Madapusi Vasudevan
Author-email: UNKNOWN
License: UNKNOWN
Platform: UNKNOWN
Classifier: Intended Audience :: Information Technology
Classifier: Intended Audience :: System Administrators
Classifier: Operating System :: POSIX :: Linux
Classifier: Programming Language :: Python
Classifier: Programming Language :: Python :: 2
Classifier: Programming Language :: Python :: 2.7
Classifier: Programming Language :: Python :: 3.3
Classifier: Programming Language :: Python :: 3.4
